{
  "version": 1,
  "generatedAt": "2026-05-21T00:00:22.255Z",
  "repo": {
    "name": "jules-dispatch",
    "sonarKey": "jules-dispatch"
  },
  "file": {
    "path": "src/commands/sources.ts"
  },
  "counts": {
    "total": 1,
    "bySeverity": {
      "MAJOR": 1
    },
    "byType": {
      "CODE_SMELL": 1
    }
  },
  "issues": [
    {
      "key": "74129c12-c1f9-4ddc-a843-ea1480bfe557",
      "severity": "MAJOR",
      "type": "CODE_SMELL",
      "rule": "typescript:S6660",
      "line": 29,
      "message": "'If' statement should not be the only statement in 'else' block"
    }
  ]
}